aideate_scraper/__init__.py
aideate_scraper/core/__init__.py
aideate_scraper/core/doc_utils.py
aideate_scraper/core/eval.py
aideate_scraper/core/image_utils.py
aideate_scraper/core/s3_utils.py
aideate_scraper/core/schemas.py
aideate_scraper/core/scrape.py
aideate_scraper/core/scrape_playwright.py
aideate_scraper/core/scrape_utils.py
aideate_scraper/modal/__init__.py
aideate_scraper/modal/modal_client.py
aideate_scraper/modal/modal_tasks.py
aideate_blade-1.0.14.dist-info/LICENSE
aideate_blade-1.0.14.dist-info/METADATA
aideate_blade-1.0.14.dist-info/WHEEL
aideate_blade-1.0.14.dist-info/top_level.txt
aideate_blade-1.0.14.dist-info/RECORD
