Metadata-Version: 2.1
Name: aideate-blade
Version: 1.0.14
Summary: web content aideate_scraper
Author: Aideate
Author-email: xiaye@aideate.ai
License-File: LICENSE
Requires-Dist: pydantic==2.6.1
Requires-Dist: ipdb==0.13.11
Requires-Dist: simplejson==3.17.6
Requires-Dist: boto3==1.29.6
Requires-Dist: boto3[crt]==1.29.6
Requires-Dist: sqlalchemy==2.0.5.post1
Requires-Dist: scrapetube==2.3.1
Requires-Dist: overrides==7.3.1
Requires-Dist: snakemd==2.1.0
Requires-Dist: html2text==2020.1.16
Requires-Dist: playwright==1.35.0
Requires-Dist: prometheus-client==0.20.0
Requires-Dist: extraction==0.3
Requires-Dist: pdfplumber==0.11.0
Requires-Dist: stripe==5.5.0
Requires-Dist: python-magic==0.4.27
Requires-Dist: StrEnum==0.4.15
Requires-Dist: modal==0.64.110
Requires-Dist: setuptools==69.5.1
Requires-Dist: tenacity==8.3.0
Requires-Dist: httpx==0.23.3
Requires-Dist: wandb==0.17.0
Requires-Dist: docstring-parser==0.16
